flameclient/LICENSE.txt
flameclient/__init__.py
flameclient/cmd.py
flameclient/collections_abc.py
flameclient/flame.py
flameclient/logs.py
flameclient/session.py
flameclient/utils.py
flameclient/resources/__init__.py
flameclient/resources/flavors.py
flameclient/resources/floatingips.py
flameclient/resources/images.py
flameclient/resources/key_pairs.py
flameclient/resources/networks.py
flameclient/resources/ports.py
flameclient/resources/routers.py
flameclient/resources/security_groups.py
flameclient/resources/server_groups.py
flameclient/resources/servers.py
flameclient/resources/subnets.py
flameclient/resources/volumes.py
flameclient/tests/__init__.py
flameclient/tests/test_flame.py
flameclient/tests/test_utils.py
flameclient/tests/utils.py
flameclient/tests/fixtures/__init__.py
flameclient/tests/fixtures/utils.py
flameclient/tests/fixtures/openstackcloud/__init__.py
flameclient/tests/fixtures/openstackcloud/flavors.py
flameclient/tests/fixtures/openstackcloud/floatingips.py
flameclient/tests/fixtures/openstackcloud/images.py
flameclient/tests/fixtures/openstackcloud/key_pairs.py
flameclient/tests/fixtures/openstackcloud/networks.py
flameclient/tests/fixtures/openstackcloud/ports.py
flameclient/tests/fixtures/openstackcloud/routers.py
flameclient/tests/fixtures/openstackcloud/security_groups.py
flameclient/tests/fixtures/openstackcloud/server_groups.py
flameclient/tests/fixtures/openstackcloud/servers.py
flameclient/tests/fixtures/openstackcloud/subnets.py
flameclient/tests/fixtures/openstackcloud/volumes.py
flameclient/tests/fixtures/results/__init__.py
flameclient/tests/fixtures/results/flame.yaml
flameclient/tests/fixtures/results/flame_adoption_data.yaml
flameclient/tests/fixtures/results/flame_constraints.yaml
flameclient/tests/fixtures/results/flame_constraints_extract_ports.yaml
flameclient/tests/fixtures/results/flame_extract_ports.yaml
python_flameclient-1.0.0.dist-info/LICENSE.txt
python_flameclient-1.0.0.dist-info/METADATA
python_flameclient-1.0.0.dist-info/RECORD
python_flameclient-1.0.0.dist-info/WHEEL
python_flameclient-1.0.0.dist-info/entry_points.txt
python_flameclient-1.0.0.dist-info/pbr.json
python_flameclient-1.0.0.dist-info/top_level.txt
