Metadata-Version: 2.1
Name: python-flameclient
Version: 1.0.0
Summary: Automatic Heat template generation
Home-page: http://www.cloudwatt.com/
Author: Orange Cloud for Business / CloudWatt
Author-email: info@cloudwatt.com
License: MIT
Platform: UNKNOWN
Classifier: Environment :: OpenStack
Classifier: Intended Audience :: Information Technology
Classifier: Intended Audience :: System Administrators
Classifier: License :: OSI Approved :: Apache Software License
Classifier: Operating System :: POSIX :: Linux
Classifier: Programming Language :: Python
Classifier: Programming Language :: Python :: 2
Classifier: Programming Language :: Python :: 2.7
Requires-Dist: certifi (==2018.8.24)
Requires-Dist: futures (<=3.2.0,>=3.1.1)
Requires-Dist: keystoneauth1 (==3.11.0)
Requires-Dist: ndg-httpsclient (==0.5.1)
Requires-Dist: netaddr (==0.7.19)
Requires-Dist: openstacksdk (==0.17.2)
Requires-Dist: os-client-config (==1.31.2)
Requires-Dist: pbr (==4.2.0)
Requires-Dist: pyasn1 (==0.4.4)
Requires-Dist: pyOpenSSL (==18.0.0)
Requires-Dist: python-cinderclient (==4.0.1)
Requires-Dist: python-glanceclient (==2.12.1)
Requires-Dist: python-heatclient (==1.16.1)
Requires-Dist: python-keystoneclient (==3.17.0)
Requires-Dist: python-neutronclient (==6.10.0)
Requires-Dist: python-novaclient (==11.0.0)
Requires-Dist: python-openstackclient (==3.16.1)
Requires-Dist: python-swiftclient (==3.6.0)
Requires-Dist: PyYAML (==3.13)
Requires-Dist: shade (==1.29.0)
